dash_sortable_tree/DndTreeEditor.py
dash_sortable_tree/__init__.py
dash_sortable_tree/_imports_.py
dash_sortable_tree/dash_dndkit_tree.min.js
dash_sortable_tree/dash_dndkit_tree.min.js.LICENSE.txt
dash_sortable_tree/dash_dndkit_tree.min.js.map
dash_sortable_tree/dash_sortable_tree.min.js
dash_sortable_tree/dash_sortable_tree.min.js.LICENSE.txt
dash_sortable_tree/dash_sortable_tree.min.js.map
dash_sortable_tree/metadata.json
dash_sortable_tree/package-info.json
dash_sortable_tree/proptypes.js
dash_sortable_tree-0.0.7.dist-info/licenses/LICENSE
dash_sortable_tree-0.0.7.dist-info/METADATA
dash_sortable_tree-0.0.7.dist-info/WHEEL
dash_sortable_tree-0.0.7.dist-info/top_level.txt
dash_sortable_tree-0.0.7.dist-info/RECORD
