Metadata-Version: 2.4
Name: dash_sortable_tree
Version: 0.0.7
Summary: A Dash component wrapping dnd-kit to edit and reorder hierarchical trees with drag & drop.
Home-page: https://github.com/marianstefi20/dash-sortable-tree
Author: Marian Stefanescu <marianstefi20@gmail.com>
License: MIT
Project-URL: Homepage, https://github.com/marianstefi20/dash-sortable-tree
Project-URL: Source, https://github.com/marianstefi20/dash-sortable-tree
Project-URL: Bug Tracker, https://github.com/marianstefi20/dash-sortable-tree/issues
Classifier: Framework :: Dash
License-File: LICENSE
Dynamic: author
Dynamic: classifier
Dynamic: description
Dynamic: description-content-type
Dynamic: home-page
Dynamic: license
Dynamic: license-file
Dynamic: project-url
Dynamic: summary
